configdoctor/__init__.py
configdoctor-0.1.0.dist-info/METADATA
configdoctor-0.1.0.dist-info/WHEEL
configdoctor-0.1.0.dist-info/entry_points.txt
configdoctor-0.1.0.dist-info/licenses/LICENSE
configdoctor-0.1.0.dist-info/RECORD
