Metadata-Version: 2.4
Name: configdoctor
Version: 0.1.0
Summary: Add your description here
Author-email: Alexeev Bronislav <alexeev.dev@mail.ru>
License-File: LICENSE
Requires-Python: >=3.11
Requires-Dist: configparser>=7.2.0
Requires-Dist: orjson>=3.11.3
Requires-Dist: pathspec>=0.12.1
Requires-Dist: pyyaml>=6.0.2
Requires-Dist: rich>=14.1.0
Requires-Dist: toml>=0.10.2
